nexustrader/__init__.py
nexustrader/aggregation.py
nexustrader/backends/__init__.py
nexustrader/backends/db.py
nexustrader/backends/db_postgresql.py
nexustrader/backends/db_sqlite.py
nexustrader/base/__init__.py
nexustrader/base/api_client.py
nexustrader/base/connector.py
nexustrader/base/ems.py
nexustrader/base/exchange.py
nexustrader/base/oms.py
nexustrader/base/retry.py
nexustrader/base/sms.py
nexustrader/base/ws_client.py
nexustrader/cli/__init__.py
nexustrader/cli/app.py
nexustrader/cli/commands/__init__.py
nexustrader/cli/main.py
nexustrader/cli/monitor/__init__.py
nexustrader/cli/monitor/state_exporter.py
nexustrader/cli/widgets/__init__.py
nexustrader/cli/widgets/balances.py
nexustrader/cli/widgets/dashboard.py
nexustrader/cli/widgets/positions.py
nexustrader/config.py
nexustrader/constants.py
nexustrader/core/__init__.py
nexustrader/core/cache.py
nexustrader/core/connection.py
nexustrader/core/entity.py
nexustrader/core/nautilius_core.py
nexustrader/core/registry.py
nexustrader/engine.py
nexustrader/error.py
nexustrader/exchange/__init__.py
nexustrader/exchange/base_factory.py
nexustrader/exchange/binance/__init__.py
nexustrader/exchange/binance/connector.py
nexustrader/exchange/binance/constants.py
nexustrader/exchange/binance/ems.py
nexustrader/exchange/binance/error.py
nexustrader/exchange/binance/exchange.py
nexustrader/exchange/binance/factory.py
nexustrader/exchange/binance/oms.py
nexustrader/exchange/binance/rest_api.py
nexustrader/exchange/binance/schema.py
nexustrader/exchange/binance/websockets.py
nexustrader/exchange/bitget/__init__.py
nexustrader/exchange/bitget/connector.py
nexustrader/exchange/bitget/constants.py
nexustrader/exchange/bitget/ems.py
nexustrader/exchange/bitget/error.py
nexustrader/exchange/bitget/exchange.py
nexustrader/exchange/bitget/factory.py
nexustrader/exchange/bitget/oms.py
nexustrader/exchange/bitget/rest_api.py
nexustrader/exchange/bitget/schema.py
nexustrader/exchange/bitget/websockets.py
nexustrader-0.2.45.dist-info/METADATA
nexustrader-0.2.45.dist-info/WHEEL
nexustrader-0.2.45.dist-info/entry_points.txt
nexustrader-0.2.45.dist-info/licenses/LICENSE
nexustrader-0.2.45.dist-info/RECORD
