Metadata-Version: 2.4
Name: nexustrader
Version: 0.2.45
Summary: fastest python trading bot
License: MIT
License-File: LICENSE
Author: River-Shi
Author-email: nachuan.shi.quant@gmail.com
Requires-Python: >=3.11,<3.14
Classifier: License :: OSI Approved :: MIT License
Classifier: Programming Language :: Python :: 3
Classifier: Programming Language :: Python :: 3.11
Classifier: Programming Language :: Python :: 3.12
Classifier: Programming Language :: Python :: 3.13
Requires-Dist: aiosqlite (>=0.21.0,<0.22.0)
Requires-Dist: apscheduler (>=3.11.0,<4.0.0)
Requires-Dist: asyncpg (>=0.30.0)
Requires-Dist: bcrypt (>=4.2.1,<5.0.0)
Requires-Dist: ccxt (>=4.5.34)
Requires-Dist: certifi (>=2025.1.31,<2026.0.0)
Requires-Dist: click (>=8.1.0)
Requires-Dist: cython (>=3.0.11,<4.0.0)
Requires-Dist: dynaconf[redis] (>=3.2.12)
Requires-Dist: eth-account (>=0.13.7)
Requires-Dist: fastapi (>=0.117.1)
Requires-Dist: flashduty-sdk (>=0.1.1)
Requires-Dist: httpx (>=0.28.1)
Requires-Dist: msgspec (>=0.19.0,<0.20.0)
Requires-Dist: nexuslog (>=0.4.4)
Requires-Dist: numpy (>=1.26.4,<2.2.1)
Requires-Dist: pandas (>=2.3.3,<3.0.0)
Requires-Dist: pathlib (>=1.0.1,<2.0.0)
Requires-Dist: picows (>=1.10.2)
Requires-Dist: psycopg2-binary (>=2.9.10)
Requires-Dist: pycryptodome (>=3.23.0)
Requires-Dist: redis (>=5.2.1,<6.0.0)
Requires-Dist: returns (>=0.24.0,<0.25.0)
Requires-Dist: textual (>=0.85.0)
Requires-Dist: throttled-py (>=2.2.3)
Requires-Dist: typing-extensions (>=4.12.2)
Requires-Dist: uvicorn (>=0.36.0)
Requires-Dist: uvloop (>=0.21.0)
Requires-Dist: walras-nexuscore (>=0.1.3)
Requires-Dist: zmq (>=0.0.0,<0.0.1)
